ccAFv2/__init__.py
ccAFv2/ccAF_v2.py
ccAFv2/ccAFv2.py
ccAFv2/ccAFv2_classes.txt
ccAFv2/ccAFv2_genes.csv
ccAFv2/ccAFv2_model.h5
ccAFv2-2.0.0.dist-info/LICENSE
ccAFv2-2.0.0.dist-info/METADATA
ccAFv2-2.0.0.dist-info/WHEEL
ccAFv2-2.0.0.dist-info/top_level.txt
ccAFv2-2.0.0.dist-info/RECORD
