Metadata-Version: 2.1
Name: ccAFv2
Version: 2.0.0
Summary: Classify scRNA-seq profiling with highly resolved cell cycle phases.
Home-page: https://github.com/plaisier-lab/ccAFv2_py
Author: Christopher Plaisier
Author-email: plaisier@asu.edu
License: GNU General Public License v3.0
Platform: UNKNOWN
Classifier: License :: OSI Approved :: GNU Affero General Public License v3
Classifier: Topic :: Scientific/Engineering :: Bio-Informatics
Classifier: Topic :: Scientific/Engineering :: Medical Science Apps.
Classifier: Programming Language :: Python :: 3
Classifier: Programming Language :: Python :: 3.7
License-File: LICENSE
Requires-Dist: importlib-resources
Requires-Dist: keras
Requires-Dist: numpy
Requires-Dist: pandas
Requires-Dist: scipy
Requires-Dist: tensorflow
